modelbox/__init__.py
modelbox/client.py
modelbox/lightning_logger.py
modelbox/modelbox.py
modelbox/notebook_widgets.py
modelbox/resource_usage.py
modelbox/service_pb2.py
modelbox/service_pb2_grpc.py
modelbox-0.0.5.dist-info/LICENSE
modelbox-0.0.5.dist-info/METADATA
modelbox-0.0.5.dist-info/WHEEL
modelbox-0.0.5.dist-info/top_level.txt
modelbox-0.0.5.dist-info/RECORD
