Metadata-Version: 2.1
Name: modelbox
Version: 0.0.5
Summary: Client Library of the ModelBox Service
Home-page: https://github.com/tensorland/modelbox
Author: Diptanu Gon Choudhury
Author-email: diptanuc@gmail.com
Classifier: Programming Language :: Python :: 3.7
Classifier: License :: OSI Approved :: Apache Software License
Classifier: Operating System :: OS Independent
Requires-Python: >=3.7
License-File: LICENSE
Requires-Dist: grpcio (>=1.46.1)
Requires-Dist: grpcio-tools (>=1.46.1)
Requires-Dist: protobuf (>=3.20.1)
Requires-Dist: tabulate (>=0.8.10)
